pypeds/__init__.py
pypeds/archive.py
pypeds/datasets.py
pypeds/ipeds.py
pypeds/views.py
pypeds/viz.py
pypeds-2023.820.dist-info/LICENSE.txt
pypeds-2023.820.dist-info/WHEEL
pypeds-2023.820.dist-info/METADATA
pypeds-2023.820.dist-info/RECORD
