Metadata-Version: 2.1
Name: pypeds
Version: 2023.820
Summary: A python package to help facilitate the collection and analysis of education-related datasets. 
Home-page: https://github.com/Btibert3/pypeds
License: UNKNOWN
Author: Brock Tibert
Author-email: btibert3@gmail.com
Maintainer: theletterjeff
Requires-Python: >=3.6
Requires-Dist: requests
Requires-Dist: pandas
Requires-Dist: altair
Requires-Dist: dfply
Requires-Dist: numpy
Requires-Dist: xlrd
